<annotation>
	<folder>edge_detection_images</folder>
	<filename>img316.png</filename>
	<path>/Users/amiteshdeshpande/Desktop/GoogleChrome-DinoAI/edge_detection_images/img316.png</path>
	<source>
		<database>Unknown</database>
	</source>
	<size>
		<width>2880</width>
		<height>1800</height>
		<depth>1</depth>
	</size>
	<segmented>0</segmented>
	<object>
		<name>Game_Over</name>
		<pose>Unspecified</pose>
		<truncated>0</truncated>
		<difficult>0</difficult>
		<bndbox>
			<xmin>1362</xmin>
			<ymin>1012</ymin>
			<xmax>1523</xmax>
			<ymax>1148</ymax>
		</bndbox>
	</object>
	<object>
		<name>Dino</name>
		<pose>Unspecified</pose>
		<truncated>0</truncated>
		<difficult>0</difficult>
		<bndbox>
			<xmin>126</xmin>
			<ymin>1096</ymin>
			<xmax>331</xmax>
			<ymax>1304</ymax>
		</bndbox>
	</object>
	<object>
		<name>Bird</name>
		<pose>Unspecified</pose>
		<truncated>0</truncated>
		<difficult>0</difficult>
		<bndbox>
			<xmin>295</xmin>
			<ymin>1126</ymin>
			<xmax>490</xmax>
			<ymax>1271</ymax>
		</bndbox>
	</object>
</annotation>
